Hardiknigame/__init__.py
Hardiknigame/main.py
Hardiknigame-0.0.3.dist-info/METADATA
Hardiknigame-0.0.3.dist-info/WHEEL
Hardiknigame-0.0.3.dist-info/top_level.txt
Hardiknigame-0.0.3.dist-info/RECORD
