Metadata-Version: 2.1
Name: Hardiknigame
Version: 0.0.3
Summary: Snakegame by Hardik
Author: Hardik Kansara
Author-email: h.kansara106@gmail.com
Keywords: python,game,snake,turtle
Classifier: Development Status :: 1 - Planning
Classifier: Intended Audience :: Developers
Classifier: Programming Language :: Python :: 3
Classifier: Operating System :: Unix
Classifier: Operating System :: MacOS :: MacOS X
Classifier: Operating System :: Microsoft :: Windows
